Acadview-1.0.1.dist-info/DESCRIPTION.rst
Acadview-1.0.1.dist-info/LICENSE.txt
Acadview-1.0.1.dist-info/METADATA
Acadview-1.0.1.dist-info/RECORD
Acadview-1.0.1.dist-info/WHEEL
Acadview-1.0.1.dist-info/metadata.json
Acadview-1.0.1.dist-info/top_level.txt
acadview/__init__.py
acadview/constants.py
acadview/input.py
